pymarketstore/__init__.py
pymarketstore/client.py
pymarketstore/grpc_client.py
pymarketstore/jsonrpc.py
pymarketstore/jsonrpc_client.py
pymarketstore/params.py
pymarketstore/results.py
pymarketstore/stream.py
pymarketstore/proto/__init__.py
pymarketstore/proto/marketstore_pb2.py
pymarketstore/proto/marketstore_pb2_grpc.py
pymarketstore-0.22.dist-info/LICENSE
pymarketstore-0.22.dist-info/METADATA
pymarketstore-0.22.dist-info/WHEEL
pymarketstore-0.22.dist-info/top_level.txt
pymarketstore-0.22.dist-info/RECORD
