Metadata-Version: 2.1
Name: pymarketstore
Version: 0.22
Summary: Marketstore python driver
Home-page: https://github.com/alpacahq/pymarketstore
Author: Alpaca
Author-email: oss@alpaca.markets
License: UNKNOWN
Keywords: database,pandas,financial,timeseries
Platform: UNKNOWN
Requires-Dist: msgpack
Requires-Dist: numpy
Requires-Dist: requests
Requires-Dist: pandas
Requires-Dist: six
Requires-Dist: urllib3
Requires-Dist: websocket-client
Requires-Dist: protobuf (>=3.11.3)
Requires-Dist: grpcio
